odoo9_addon_openeducat_exam-9.0.2.4.0-py2.7-nspkg.pth
odoo9_addon_openeducat_exam-9.0.2.4.0.dist-info/top_level.txt
odoo9_addon_openeducat_exam-9.0.2.4.0.dist-info/WHEEL
odoo9_addon_openeducat_exam-9.0.2.4.0.dist-info/RECORD
odoo9_addon_openeducat_exam-9.0.2.4.0.dist-info/metadata.json
odoo9_addon_openeducat_exam-9.0.2.4.0.dist-info/DESCRIPTION.rst
odoo9_addon_openeducat_exam-9.0.2.4.0.dist-info/METADATA
odoo9_addon_openeducat_exam-9.0.2.4.0.dist-info/namespace_packages.txt
odoo_addons/openeducat_exam/__openerp__.py
odoo_addons/openeducat_exam/__init__.py
odoo_addons/openeducat_exam/exam_menu.xml
odoo_addons/openeducat_exam/security/ir.model.access.csv
odoo_addons/openeducat_exam/report/student_marksheet.py
odoo_addons/openeducat_exam/report/report_ticket.xml
odoo_addons/openeducat_exam/report/student_marksheet.xml
odoo_addons/openeducat_exam/report/__init__.py
odoo_addons/openeducat_exam/report/student_hall_ticket_report.py
odoo_addons/openeducat_exam/report/report_menu.xml
odoo_addons/openeducat_exam/report/report_exam_student_label.xml
odoo_addons/openeducat_exam/report/report_exam_student_lable.py
odoo_addons/openeducat_exam/models/exam_room.py
odoo_addons/openeducat_exam/models/result_template.py
odoo_addons/openeducat_exam/models/exam_res_allocation.py
odoo_addons/openeducat_exam/models/exam_type.py
odoo_addons/openeducat_exam/models/exam_attendees.py
odoo_addons/openeducat_exam/models/min_clearance_criteria.py
odoo_addons/openeducat_exam/models/result_template_line.py
odoo_addons/openeducat_exam/models/exam.py
odoo_addons/openeducat_exam/models/__init__.py
odoo_addons/openeducat_exam/models/exam_session.py
odoo_addons/openeducat_exam/models/result_exam_line.py
odoo_addons/openeducat_exam/models/marksheet_register.py
odoo_addons/openeducat_exam/models/marksheet_line.py
odoo_addons/openeducat_exam/models/pass_status.py
odoo_addons/openeducat_exam/models/result_line.py
odoo_addons/openeducat_exam/i18n/openeducat_exam.pot
odoo_addons/openeducat_exam/wizard/__init__.py
odoo_addons/openeducat_exam/wizard/student_hall_tickets_wizard.py
odoo_addons/openeducat_exam/wizard/student_hall_tickets_wizard_view.xml
odoo_addons/openeducat_exam/views/result_template_view.xml
odoo_addons/openeducat_exam/views/marksheet_line_view.xml
odoo_addons/openeducat_exam/views/exam_attendees_view.xml
odoo_addons/openeducat_exam/views/result_line_view.xml
